LICENSE
README.md
setup.py
esets/__init__.py
esets/inf.py
esets.egg-info/PKG-INFO
esets.egg-info/SOURCES.txt
esets.egg-info/dependency_links.txt
esets.egg-info/top_level.txt
tests/__init__.py
tests/test_eset.py
tests/test_inf.py