Metadata-Version: 2.1
Name: esets
Version: 0.1.0
Summary: Extended sets
Home-page: https://github.com/freywaid/esets
Author: Frey Waid
Author-email: logophage1@gmail.com
License: MIT license
Classifier: Development Status :: 3 - Alpha
Classifier: Programming Language :: Python :: 3
Classifier: License :: OSI Approved :: MIT License
Classifier: Operating System :: OS Independent
Requires-Python: >=3.7
License-File: LICENSE
